leafdb.py
leafdb-1.0.4.dist-info/METADATA
leafdb-1.0.4.dist-info/WHEEL
leafdb-1.0.4.dist-info/top_level.txt
leafdb-1.0.4.dist-info/RECORD
